{
    "D:/TRASH/tv\\input\\books\\b1.png": {
        "fileSize": 1143253
    },
    "D:/TRASH/tv\\input\\books\\b2.png": {
        "fileSize": 1517648
    },
    "D:/TRASH/tv\\input\\books\\b3.png": {
        "fileSize": 422338
    },
    "D:/TRASH/tv\\input\\books\\b4.png": {
        "fileSize": 1209903
    },
    "D:/TRASH/tv\\input\\substance_books_project\\tv_books_cover_BaseColor_Utility - sRGB - Texture.1001.tif": {
        "fileSize": 726934
    },
    "D:/TRASH/tv\\input\\substance_books_project\\tv_books_cover_Height_Utility - Raw.1001.tif": {
        "fileSize": 222046
    },
    "D:/TRASH/tv\\input\\substance_books_project\\tv_books_cover_Metallic_Utility - Raw.1001.tif": {
        "fileSize": 197932
    },
    "D:/TRASH/tv\\input\\substance_books_project\\tv_books_cover_Normal_Utility - Raw.1001.tif": {
        "fileSize": 1474104
    },
    "D:/TRASH/tv\\input\\substance_books_project\\tv_books_cover_Roughness_Utility - Raw.1001.tif": {
        "fileSize": 2526894
    },
    "D:/TRASH/tv\\input\\wood_board_wbojfbbg\\wbojfbbg.json": {
        "fileSize": 42247
    },
    "D:/TRASH/tv\\input\\wood_parquet_ufipfbmew\\ufipfbmew.json": {
        "fileSize": 42375
    },
    "D:/TRASH/tv\\input\\wood_board_wbojfbbg\\wbojfbbg_8K_Albedo.jpg": {
        "fileSize": 21001614
    },
    "D:/TRASH/tv\\input\\wood_parquet_ufipfbmew\\ufipfbmew_8K_Albedo.jpg": {
        "fileSize": 48542162
    },
    "D:/TRASH/tv\\input\\wood_board_wbojfbbg\\wbojfbbg_8K_AO.jpg": {
        "fileSize": 8370353
    },
    "D:/TRASH/tv\\input\\wood_parquet_ufipfbmew\\ufipfbmew_8K_AO.jpg": {
        "fileSize": 5273108
    },
    "D:/TRASH/tv\\input\\wood_board_wbojfbbg\\wbojfbbg_8K_Displacement.exr": {
        "fileSize": 94713264
    },
    "D:/TRASH/tv\\input\\wood_parquet_ufipfbmew\\ufipfbmew_8K_Displacement.exr": {
        "fileSize": 173652228
    },
    "D:/TRASH/tv\\input\\wood_board_wbojfbbg\\wbojfbbg_8K_Displacement.jpg": {
        "fileSize": 4100204
    },
    "D:/TRASH/tv\\input\\wood_parquet_ufipfbmew\\ufipfbmew_8K_Displacement.jpg": {
        "fileSize": 6600319
    },
    "D:/TRASH/tv\\input\\wood_board_wbojfbbg\\wbojfbbg_8K_Normal.jpg": {
        "fileSize": 12432107
    },
    "D:/TRASH/tv\\input\\wood_parquet_ufipfbmew\\ufipfbmew_8K_Normal.jpg": {
        "fileSize": 45027806
    },
    "D:/TRASH/tv\\input\\wood_parquet_ufipfbmew\\ufipfbmew_8K_Roughness.jpg": {
        "fileSize": 38713201
    },
    "D:/TRASH/tv\\input\\wood_board_wbojfbbg\\wbojfbbg_8K_Roughness.jpg": {
        "fileSize": 11063963
    },
    "D:/TRASH/tv\\input\\wood_parquet_ufipfbmew\\ufipfbmew_Preview.png": {
        "fileSize": 271597
    },
    "D:/TRASH/tv\\input\\wood_board_wbojfbbg\\wbojfbbg_Preview.png": {
        "fileSize": 269015
    },
    "D:/TRASH/tv\\input\\wood_plank_viriagk\\viriagk.json": {
        "fileSize": 42150
    },
    "D:/TRASH/tv\\input\\wood_plank_viriagk\\viriagk_8K_Albedo.jpg": {
        "fileSize": 22787795
    },
    "D:/TRASH/tv\\input\\wood_plank_viriagk\\viriagk_8K_AO.jpg": {
        "fileSize": 1150169
    },
    "D:/TRASH/tv\\input\\wood_plank_viriagk\\viriagk_8K_Displacement.exr": {
        "fileSize": 162024328
    },
    "D:/TRASH/tv\\input\\wood_plank_viriagk\\viriagk_8K_Displacement.jpg": {
        "fileSize": 6053540
    },
    "D:/TRASH/tv\\input\\wood_plank_viriagk\\viriagk_8K_Normal.jpg": {
        "fileSize": 10223964
    },
    "D:/TRASH/tv\\input\\wood_plank_viriagk\\viriagk_8K_Roughness.jpg": {
        "fileSize": 7732419
    },
    "D:/TRASH/tv\\input\\wood_plank_viriagk\\viriagk_Preview.png": {
        "fileSize": 259744
    },
    "D:/TRASH/tv\\input\\wood_plank_wcvieg3n\\wcvieg3n.json": {
        "fileSize": 42357
    },
    "D:/TRASH/tv\\input\\wood_plank_wcvieg3n\\wcvieg3n_8K_Albedo.jpg": {
        "fileSize": 52810340
    },
    "D:/TRASH/tv\\input\\wood_plank_wcvieg3n\\wcvieg3n_8K_AO.jpg": {
        "fileSize": 28586641
    },
    "D:/TRASH/tv\\input\\wood_plank_wcvieg3n\\wcvieg3n_8K_Displacement.exr": {
        "fileSize": 158561611
    },
    "D:/TRASH/tv\\input\\wood_plank_wcvieg3n\\wcvieg3n_8K_Displacement.jpg": {
        "fileSize": 5868014
    },
    "D:/TRASH/tv\\input\\wood_plank_wcvieg3n\\wcvieg3n_8K_Normal.jpg": {
        "fileSize": 66869242
    },
    "D:/TRASH/tv\\input\\wood_plank_wcvieg3n\\wcvieg3n_8K_Roughness.jpg": {
        "fileSize": 44778646
    },
    "D:/TRASH/tv\\input\\wood_plank_wcvieg3n\\wcvieg3n_Preview.png": {
        "fileSize": 267045
    },
    "D:/TRASH/tv\\input\\wood_veneer_vdcjfiw\\vdcjfiw.json": {
        "fileSize": 41654
    },
    "D:/TRASH/tv\\input\\wood_veneer_vdcjfiw\\vdcjfiw_8K_Albedo.jpg": {
        "fileSize": 17812309
    },
    "D:/TRASH/tv\\input\\wood_veneer_vdcjfiw\\vdcjfiw_8K_AO.jpg": {
        "fileSize": 11921066
    },
    "D:/TRASH/tv\\input\\wood_veneer_vdcjfiw\\vdcjfiw_8K_Displacement.exr": {
        "fileSize": 89279261
    },
    "D:/TRASH/tv\\input\\wood_veneer_vdcjfiw\\vdcjfiw_8K_Displacement.jpg": {
        "fileSize": 3815019
    },
    "D:/TRASH/tv\\input\\wood_veneer_vdcjfiw\\vdcjfiw_8K_Normal.jpg": {
        "fileSize": 24905557
    },
    "D:/TRASH/tv\\input\\wood_veneer_vdcjfiw\\vdcjfiw_8K_Roughness.jpg": {
        "fileSize": 9632741
    },
    "D:/TRASH/tv\\input\\wood_veneer_vdcjfiw\\vdcjfiw_Preview.png": {
        "fileSize": 237346
    },
    "D:/TRASH/tv\\output\\substance_books_v001\\tv_books_cover_BaseColor_Utility - sRGB - Texture.1001.tif": {
        "fileSize": 726934
    },
    "D:/TRASH/tv\\output\\substance_books_v001\\tv_books_cover_BaseColor_Utility - sRGB - Texture.1001.tif.tex": {
        "fileSize": 1084948
    },
    "D:/TRASH/tv\\output\\substance_books_v001\\tv_books_cover_BaseColor_Utility - sRGB - Texture_srgbtex_acescg.1001.tif.tex": {
        "fileSize": 1056286
    },
    "D:/TRASH/tv\\output\\substance_books_v001\\tv_books_cover_DiffuseColor_Utility - sRGB - Texture.1001.tif": {
        "fileSize": 816044
    },
    "D:/TRASH/tv\\output\\substance_books_v001\\tv_books_cover_Displacement_Utility - Raw.1001.tif": {
        "fileSize": 222046
    },
    "D:/TRASH/tv\\output\\substance_books_v001\\tv_books_cover_Height_Utility - Raw.1001.tif": {
        "fileSize": 222046
    },
    "D:/TRASH/tv\\output\\substance_books_v001\\tv_books_cover_Metallic_Utility - Raw.1001.tif": {
        "fileSize": 197932
    },
    "D:/TRASH/tv\\output\\substance_books_v001\\tv_books_cover_Metallic_Utility - Raw.1001.tif.tex": {
        "fileSize": 350108
    },
    "D:/TRASH/tv\\output\\substance_books_v001\\tv_books_cover_Metallic_Utility - Raw_data_acescg.1001.tif.tex": {
        "fileSize": 81003
    },
    "D:/TRASH/tv\\output\\substance_books_v001\\tv_books_cover_Normal_Utility - Raw.1001.tif": {
        "fileSize": 1474104
    },
    "D:/TRASH/tv\\output\\substance_books_v001\\tv_books_cover_Normal_Utility - Raw.1001.tif.tex": {
        "fileSize": 772939
    },
    "D:/TRASH/tv\\output\\substance_tvcontroller_v001\\tvController_tvcontroller_DiffuseColor_Utility - sRGB - Texture.1001.tif": {
        "fileSize": 653826
    },
    "D:/TRASH/tv\\output\\substance_books_v001\\tv_books_cover_Normal_Utility - Raw_data_acescg.1001.tif.tex": {
        "fileSize": 2681926
    },
    "D:/TRASH/tv\\output\\substance_tvchandelier_v001\\tvChandelier_mod_tvchandelier_BaseColor_Utility - sRGB - Texture.1001.tif": {
        "fileSize": 16656542
    },
    "D:/TRASH/tv\\output\\substance_tvcontroller_v001\\tvController_tvcontroller_Displacement_Utility - Raw.1001.tif": {
        "fileSize": 2879530
    },
    "D:/TRASH/tv\\output\\substance_books_v001\\tv_books_cover_Roughness_Utility - Raw.1001.tif": {
        "fileSize": 2526894
    },
    "D:/TRASH/tv\\output\\substance_tvchandelier_v001\\tvChandelier_mod_tvchandelier_Height_Utility - Raw.1001.tif": {
        "fileSize": 3964370
    },
    "D:/TRASH/tv\\output\\substance_books_v001\\tv_books_cover_Roughness_Utility - Raw.1001.tif.tex": {
        "fileSize": 4572227
    },
    "D:/TRASH/tv\\output\\substance_tvcontroller_v001\\tvController_tvcontroller_Normal_Utility - Raw.1001.tif": {
        "fileSize": 15170266
    },
    "D:/TRASH/tv\\output\\substance_tvchandelier_v001\\tvChandelier_mod_tvchandelier_Metallic_Utility - Raw.1001.tif": {
        "fileSize": 282326
    },
    "D:/TRASH/tv\\output\\substance_books_v001\\tv_books_cover_Roughness_Utility - Raw_data_acescg.1001.tif.tex": {
        "fileSize": 4061933
    },
    "D:/TRASH/tv\\output\\substance_tvcontroller_v001\\tvController_tvcontroller_SpecularFaceColor_Utility - sRGB - Texture.1001.tif": {
        "fileSize": 393474
    },
    "D:/TRASH/tv\\output\\substance_tvchandelier_v001\\tvChandelier_mod_tvchandelier_Normal_Utility - Raw.1001.tif": {
        "fileSize": 17350622
    },
    "D:/TRASH/tv\\output\\substance_books_v001\\tv_books_cover_SpecularFaceColor_Utility - sRGB - Texture.1001.tif": {
        "fileSize": 521486
    },
    "D:/TRASH/tv\\output\\substance_tvcontroller_v001\\tvController_tvcontroller_SpecularRoughness_Utility - Raw.1001.tif": {
        "fileSize": 2291650
    },
    "D:/TRASH/tv\\output\\substance_tvchandelier_v001\\tvChandelier_mod_tvchandelier_Roughness_Utility - Raw.1001.tif": {
        "fileSize": 3834150
    },
    "D:/TRASH/tv\\output\\substance_books_v001\\tv_books_cover_SpecularFaceColor_Utility - sRGB - Texture.1001.tif.tex": {
        "fileSize": 606238
    },
    "D:/TRASH/tv\\output\\substance_books_v001\\tv_books_cover_SpecularFaceColor_Utility - sRGB - Texture_srgbtex_acescg.1001.tif.tex": {
        "fileSize": 616260
    },
    "D:/TRASH/tv\\output\\substance_books_v001\\tv_books_cover_SpecularRoughness_Utility - Raw.1001.tif": {
        "fileSize": 2526894
    },
    "D:/TRASH/tv\\output\\substance_tvheater_v001\\tvHeater_mod_tvHeater_DiffuseColor_Utility - sRGB - Texture.1001.tif": {
        "fileSize": 13379580
    },
    "D:/TRASH/tv\\output\\substance_tvdoor_v001\\tvDoor_tvdoor_BaseColor_Utility - sRGB - Texture.1001.tif": {
        "fileSize": 17581624
    },
    "D:/TRASH/tv\\output\\substance_tvdoor_v002\\tvDoor_tvdoor_DiffuseColor_Utility - sRGB - Texture.1001.tif": {
        "fileSize": 16240790
    },
    "D:/TRASH/tv\\output\\substance_tvheater_v001\\tvHeater_mod_tvHeater_Displacement_Utility - Raw.1001.tif": {
        "fileSize": 5112648
    },
    "D:/TRASH/tv\\output\\substance_tvdoor_v001\\tvDoor_tvdoor_DiffuseColor_Utility - sRGB - Texture.1001.tif": {
        "fileSize": 16240804
    },
    "D:/TRASH/tv\\output\\substance_tvdoor_v002\\tvDoor_tvdoor_Displacement_Utility - Raw.1001.tif": {
        "fileSize": 4346322
    },
    "D:/TRASH/tv\\output\\substance_tvheater_v001\\tvHeater_mod_tvHeater_Normal_Utility - Raw.1001.tif": {
        "fileSize": 21146326
    },
    "D:/TRASH/tv\\output\\substance_tvdoor_v001\\tvDoor_tvdoor_Displacement_Utility - Raw.1001.tif": {
        "fileSize": 4377238
    },
    "D:/TRASH/tv\\output\\substance_tvdoor_v002\\tvDoor_tvdoor_Normal_Utility - Raw.1001.tif": {
        "fileSize": 21391546
    },
    "D:/TRASH/tv\\output\\substance_tvdoor_v003\\tvDoor_tvdoor_DiffuseColor_Utility - sRGB - Texture.1001.tif": {
        "fileSize": 16240790
    },
    "D:/TRASH/tv\\output\\substance_tvheater_v001\\tvHeater_mod_tvHeater_SpecularFaceColor_Utility - sRGB - Texture.1001.tif": {
        "fileSize": 393474
    },
    "D:/TRASH/tv\\output\\substance_tvdoor_v001\\tvDoor_tvdoor_Height_Utility - Raw.1001.tif": {
        "fileSize": 4377238
    },
    "D:/TRASH/tv\\output\\substance_tvdoor_v003\\tvDoor_tvdoor_Displacement_Utility - Raw.1001.tif": {
        "fileSize": 4169802
    },
    "D:/TRASH/tv\\output\\substance_tvheater_v001\\tvHeater_mod_tvHeater_SpecularRoughness_Utility - Raw.1001.tif": {
        "fileSize": 3119692
    },
    "D:/TRASH/tv\\output\\substance_tvdoor_v002\\tvDoor_tvdoor_Presence_Utility - Raw.1001.tif": {
        "fileSize": 165946
    },
    "D:/TRASH/tv\\output\\substance_tvdoor_v001\\tvDoor_tvdoor_Metallic_Utility - Raw.1001.tif": {
        "fileSize": 161428
    },
    "D:/TRASH/tv\\output\\substance_tvdoor_v003\\tvDoor_tvdoor_Normal_Utility - Raw.1001.tif": {
        "fileSize": 20645254
    },
    "D:/TRASH/tv\\output\\substance_tvdoor_v002\\tvDoor_tvdoor_SpecularFaceColor_Utility - sRGB - Texture.1001.tif": {
        "fileSize": 399090
    },
    "D:/TRASH/tv\\output\\substance_tvdoor_v001\\tvDoor_tvdoor_Normal_Utility - Raw.1001.tif": {
        "fileSize": 21613502
    },
    "D:/TRASH/tv\\output\\substance_tvdoor_v003\\tvDoor_tvdoor_Presence_Utility - Raw.1001.tif": {
        "fileSize": 165946
    },
    "D:/TRASH/tv\\output\\substance_tvdoor_v002\\tvDoor_tvdoor_SpecularRoughness_Utility - Raw.1001.tif": {
        "fileSize": 3332372
    },
    "D:/TRASH/tv\\output\\substance_tvdoor_v001\\tvDoor_tvdoor_Presence_Utility - Raw.1001.tif": {
        "fileSize": 165946
    },
    "D:/TRASH/tv\\output\\substance_tvdoor_v003\\tvDoor_tvdoor_SpecularFaceColor_Utility - sRGB - Texture.1001.tif": {
        "fileSize": 399090
    },
    "D:/TRASH/tv\\output\\substance_tvdoor_v001\\tvDoor_tvdoor_Roughness_Utility - Raw.1001.tif": {
        "fileSize": 3332272
    },
    "D:/TRASH/tv\\output\\substance_tvdoor_v003\\tvDoor_tvdoor_SpecularRoughness_Utility - Raw.1001.tif": {
        "fileSize": 3332372
    },
    "D:/TRASH/tv\\output\\substance_tvdoor_v001\\tvDoor_tvdoor_SpecularFaceColor_Utility - sRGB - Texture.1001.tif": {
        "fileSize": 399090
    },
    "D:/TRASH/tv\\output\\substance_tvshelf_v001\\tvShelf_tvshelf_DiffuseColor_Utility - sRGB - Texture.1001.png": {
        "fileSize": 8830264
    },
    "D:/TRASH/tv\\output\\substance_tvdoor_v001\\tvDoor_tvdoor_SpecularRoughness_Utility - Raw.1001.tif": {
        "fileSize": 3332272
    },
    "D:/TRASH/tv\\output\\substance_tvshelf_v001\\tvShelf_tvshelf_Displacement_Utility - Raw.1001.png": {
        "fileSize": 2151876
    },
    "D:/TRASH/tv\\output\\substance_tvshelf_v001\\tvShelf_tvshelf_Normal_Utility - Raw.1001.png": {
        "fileSize": 7925456
    },
    "D:/TRASH/tv\\output\\substance_tvshelf_v001\\tvShelf_tvshelf_Presence_Utility - Raw.1001.png": {
        "fileSize": 44018
    },
    "D:/TRASH/tv\\output\\substance_tvshelf_v001\\tvShelf_tvshelf_SpecularFaceColor_Utility - sRGB - Texture.1001.png": {
        "fileSize": 29467
    },
    "D:/TRASH/tv\\output\\substance_tvshelf_v001\\tvShelf_tvshelf_SpecularRoughness_Utility - Raw.1001.png": {
        "fileSize": 868940
    },
    "D:/TRASH/tv\\output\\substance_tvshelf_v002\\tvShelf_tvbook_DiffuseColor_Utility - sRGB - Texture.1001.tif": {
        "fileSize": 4920790
    },
    "D:/TRASH/tv\\output\\substance_tvshelf_v002\\tvShelf_tvbook_Displacement_Utility - Raw.1001.tif": {
        "fileSize": 162038
    },
    "D:/TRASH/tv\\output\\substance_tvshelf_v002\\tvShelf_tvbook_Normal_Utility - Raw.1001.tif": {
        "fileSize": 401384
    },
    "D:/TRASH/tv\\output\\substance_tvshelf_v002\\tvShelf_tvbook_Presence_Utility - Raw.1001.tif": {
        "fileSize": 300468
    },
    "D:/TRASH/tv\\output\\substance_tvsofa_v001\\tvsofa_mod_tvsofa_DiffuseColor_Utility - sRGB - Texture.1001.tif": {
        "fileSize": 25253120
    },
    "D:/TRASH/tv\\output\\substance_tvshelf_v002\\tvShelf_tvbook_SpecularFaceColor_Utility - sRGB - Texture.1001.tif": {
        "fileSize": 393474
    },
    "D:/TRASH/tv\\output\\substance_tvsofa_v001\\tvsofa_mod_tvsofa_Displacement_Utility - Raw.1001.tif": {
        "fileSize": 6102826
    },
    "D:/TRASH/tv\\output\\substance_tvshelf_v002\\tvShelf_tvbook_SpecularRoughness_Utility - Raw.1001.tif": {
        "fileSize": 727100
    },
    "D:/TRASH/tv\\output\\substance_tvsofa_v001\\tvsofa_mod_tvsofa_Normal_Utility - Raw.1001.tif": {
        "fileSize": 26791080
    },
    "D:/TRASH/tv\\output\\substance_tvshelf_v002\\tvShelf_tvshelf_2_DiffuseColor_Utility - sRGB - Texture.1001.tif": {
        "fileSize": 14534970
    },
    "D:/TRASH/tv\\output\\substance_tvsofa_v001\\tvsofa_mod_tvsofa_SpecularFaceColor_Utility - sRGB - Texture.1001.tif": {
        "fileSize": 393474
    },
    "D:/TRASH/tv\\output\\substance_tvsofa_v001\\tvsofa_mod_tvsofa_SpecularRoughness_Utility - Raw.1001.tif": {
        "fileSize": 3597020
    },
    "D:/TRASH/tv\\output\\substance_tvshelf_v002\\tvShelf_tvshelf_2_Displacement_Utility - Raw.1001.tif": {
        "fileSize": 3832846
    },
    "D:/TRASH/tv\\output\\substance_tvshelf_v002\\tvShelf_tvshelf_2_Normal_Utility - Raw.1001.tif": {
        "fileSize": 16867368
    },
    "D:/TRASH/tv\\output\\substance_tvshelf_v002\\tvShelf_tvshelf_2_SpecularFaceColor_Utility - sRGB - Texture.1001.tif": {
        "fileSize": 393474
    },
    "D:/TRASH/tv\\output\\substance_tvshelf_v002\\tvShelf_tvshelf_2_SpecularRoughness_Utility - Raw.1001.tif": {
        "fileSize": 1304858
    },
    "D:/TRASH/tv\\output\\substance_tvtable_v001\\tvTable_PxrSurface1SG_BaseColor_Utility - sRGB - Texture.1001.tif": {
        "fileSize": 20331444
    },
    "D:/TRASH/tv\\output\\substance_tvtable_v001\\tvTable_PxrSurface1SG_BaseColor_Utility - sRGB - Texture.1011.tif": {
        "fileSize": 1264516
    },
    "D:/TRASH/tv\\output\\substance_tvtable_v001\\tvTable_PxrSurface1SG_DiffuseColor_Utility - sRGB - Texture.1001.tif": {
        "fileSize": 19101756
    },
    "D:/TRASH/tv\\output\\substance_tvtable_v001\\tvTable_PxrSurface1SG_DiffuseColor_Utility - sRGB - Texture.1011.tif": {
        "fileSize": 1264516
    },
    "D:/TRASH/tv\\output\\substance_tvtable_v001\\tvTable_PxrSurface1SG_Displacement_Utility - Raw.1001.tif": {
        "fileSize": 4276966
    },
    "D:/TRASH/tv\\output\\substance_tvtable_v001\\tvTable_PxrSurface1SG_Displacement_Utility - Raw.1011.tif": {
        "fileSize": 386102
    },
    "D:/TRASH/tv\\output\\substance_tvtable_v001\\tvTable_PxrSurface1SG_Height_Utility - Raw.1001.tif": {
        "fileSize": 4276966
    },
    "D:/TRASH/tv\\output\\substance_tvtelevision_v001\\initialShadingGroup_Base_color_Utility - sRGB - Texture_1001.tif": {
        "fileSize": 13263376
    },
    "D:/TRASH/tv\\output\\substance_tvtable_v001\\tvTable_PxrSurface1SG_Height_Utility - Raw.1011.tif": {
        "fileSize": 386102
    },
    "D:/TRASH/tv\\output\\substance_tvtelevision_v001\\initialShadingGroup_Height_Utility - Raw_1001.tif": {
        "fileSize": 2974814
    },
    "D:/TRASH/tv\\output\\substance_tvtable_v001\\tvTable_PxrSurface1SG_Metallic_Utility - Raw.1001.tif": {
        "fileSize": 270150
    },
    "D:/TRASH/tv\\output\\substance_tvtelevision_v002\\tvTelevision_initialShadingGroup_BaseColor_Utility - sRGB - Texture.1001.tif": {
        "fileSize": 13041710
    },
    "D:/TRASH/tv\\output\\substance_tvtelevision_v001\\initialShadingGroup_Metallic_Utility - Raw_1001.tif": {
        "fileSize": 163344
    },
    "D:/TRASH/tv\\output\\substance_tvtable_v001\\tvTable_PxrSurface1SG_Metallic_Utility - Raw.1011.tif": {
        "fileSize": 158966
    },
    "D:/TRASH/tv\\output\\substance_tvtelevision_v002\\tvTelevision_initialShadingGroup_Height_Utility - Raw.1001.tif": {
        "fileSize": 2974814
    },
    "D:/TRASH/tv\\output\\substance_tvtelevision_v001\\initialShadingGroup_Mixed_AO_Utility - Raw_1001.tif": {
        "fileSize": 2327576
    },
    "D:/TRASH/tv\\output\\substance_tvtable_v001\\tvTable_PxrSurface1SG_Normal_Utility - Raw.1001.tif": {
        "fileSize": 19374048
    },
    "D:/TRASH/tv\\output\\substance_tvtelevision_v002\\tvTelevision_initialShadingGroup_Metallic_Utility - Raw.1001.tif": {
        "fileSize": 163344
    },
    "D:/TRASH/tv\\output\\substance_tvtelevision_v001\\initialShadingGroup_Normal_DirectX_Utility - Raw_1001.tif": {
        "fileSize": 13352500
    },
    "D:/TRASH/tv\\output\\substance_tvventilator_v001\\tvVentilator_tvVentilator_DiffuseColor_Utility - sRGB - Texture.1001.tif": {
        "fileSize": 11795280
    },
    "D:/TRASH/tv\\output\\substance_tvtable_v001\\tvTable_PxrSurface1SG_Normal_Utility - Raw.1011.tif": {
        "fileSize": 1165956
    },
    "D:/TRASH/tv\\output\\substance_tvtelevision_v002\\tvTelevision_initialShadingGroup_Normal_Utility - Raw.1001.tif": {
        "fileSize": 13352500
    },
    "D:/TRASH/tv\\output\\substance_tvtelevision_v001\\initialShadingGroup_Normal_Utility - Raw_1001.tif": {
        "fileSize": 2723064
    },
    "D:/TRASH/tv\\output\\substance_tvventilator_v001\\tvVentilator_tvVentilator_Displacement_Utility - Raw.1001.tif": {
        "fileSize": 1074606
    },
    "D:/TRASH/tv\\output\\substance_tvtable_v001\\tvTable_PxrSurface1SG_Presence_Utility - Raw.1001.tif": {
        "fileSize": 171896
    },
    "D:/TRASH/tv\\output\\substance_tvtelevision_v001\\initialShadingGroup_Roughness_Utility - Raw_1001.tif": {
        "fileSize": 2593896
    },
    "D:/TRASH/tv\\output\\substance_tvtelevision_v002\\tvTelevision_initialShadingGroup_Roughness_Utility - Raw.1001.tif": {
        "fileSize": 2593896
    },
    "D:/TRASH/tv\\output\\substance_tvwalls_v001\\tv_walls_tvwalls_DiffuseColor_Utility - sRGB - Texture.1001.tif": {
        "fileSize": 22930460
    },
    "D:/TRASH/tv\\output\\substance_tvventilator_v001\\tvVentilator_tvVentilator_Normal_Utility - Raw.1001.tif": {
        "fileSize": 5619356
    },
    "D:/TRASH/tv\\output\\substance_tvtable_v001\\tvTable_PxrSurface1SG_Presence_Utility - Raw.1011.tif": {
        "fileSize": 162038
    },
    "D:/TRASH/tv\\input\\wood_board_wbojfbbg\\previews\\wbojfbbg_Popup_3840_sp.jpg": {
        "fileSize": 258738
    },
    "D:/TRASH/tv\\output\\substance_tvwalls_v001\\tv_walls_tvwalls_DiffuseColor_Utility - sRGB - Texture.1002.tif": {
        "fileSize": 24404412
    },
    "D:/TRASH/tv\\output\\substance_tvventilator_v001\\tvVentilator_tvVentilator_Presence_Utility - Raw.1001.tif": {
        "fileSize": 747576
    },
    "D:/TRASH/tv\\output\\substance_tvtable_v001\\tvTable_PxrSurface1SG_Roughness_Utility - Raw.1001.tif": {
        "fileSize": 4029836
    },
    "D:/TRASH/tv\\output\\substance_tvwalls_v001\\tv_walls_tvwalls_Displacement_Utility - Raw.1001.tif": {
        "fileSize": 4282982
    },
    "D:/TRASH/tv\\output\\substance_tvventilator_v001\\tvVentilator_tvVentilator_SpecularFaceColor_Utility - sRGB - Texture.1001.tif": {
        "fileSize": 393474
    },
    "D:/TRASH/tv\\output\\substance_tvtable_v001\\tvTable_PxrSurface1SG_Roughness_Utility - Raw.1011.tif": {
        "fileSize": 397240
    },
    "D:/TRASH/tv\\output\\substance_tvwalls_v001\\tv_walls_tvwalls_Displacement_Utility - Raw.1002.tif": {
        "fileSize": 4691414
    },
    "D:/TRASH/tv\\output\\substance_tvventilator_v001\\tvVentilator_tvVentilator_SpecularRoughness_Utility - Raw.1001.tif": {
        "fileSize": 2254354
    },
    "D:/TRASH/tv\\output\\substance_tvtable_v001\\tvTable_PxrSurface1SG_SpecularFaceColor_Utility - sRGB - Texture.1001.tif": {
        "fileSize": 814308
    },
    "D:/TRASH/tv\\output\\substance_tvwalls_v001\\tv_walls_tvwalls_Normal_Utility - Raw.1001.tif": {
        "fileSize": 23473256
    },
    "D:/TRASH/tv\\output\\substance_tvtable_v001\\tvTable_PxrSurface1SG_SpecularFaceColor_Utility - sRGB - Texture.1011.tif": {
        "fileSize": 393474
    },
    "D:/TRASH/tv\\output\\substance_tvwalls_v001\\tv_walls_tvwalls_Normal_Utility - Raw.1002.tif": {
        "fileSize": 25411728
    },
    "D:/TRASH/tv\\output\\substance_tvtable_v001\\tvTable_PxrSurface1SG_SpecularRoughness_Utility - Raw.1001.tif": {
        "fileSize": 4029836
    },
    "D:/TRASH/tv\\output\\substance_tvwalls_v001\\tv_walls_tvwalls_SpecularFaceColor_Utility - sRGB - Texture.1001.tif": {
        "fileSize": 393474
    },
    "D:/TRASH/tv\\output\\substance_tvtable_v001\\tvTable_PxrSurface1SG_SpecularRoughness_Utility - Raw.1011.tif": {
        "fileSize": 397240
    },
    "D:/TRASH/tv\\output\\substance_tvwalls_v001\\tv_walls_tvwalls_SpecularFaceColor_Utility - sRGB - Texture.1002.tif": {
        "fileSize": 393474
    },
    "D:/TRASH/tv\\output\\substance_tvwalls_v001\\tv_walls_tvwalls_SpecularRoughness_Utility - Raw.1001.tif": {
        "fileSize": 2597230
    },
    "D:/TRASH/tv\\output\\substance_tvwalls_v001\\tv_walls_tvwalls_SpecularRoughness_Utility - Raw.1002.tif": {
        "fileSize": 2741516
    },
    "D:/TRASH/tv\\input\\wood_board_wbojfbbg\\Thumbs\\1k\\wbojfbbg_1K_Albedo.jpg": {
        "fileSize": 657093
    },
    "D:/TRASH/tv\\input\\wood_board_wbojfbbg\\Thumbs\\2k\\wbojfbbg_2K_Albedo.jpg": {
        "fileSize": 2468974
    },
    "D:/TRASH/tv\\input\\wood_board_wbojfbbg\\Thumbs\\1k\\wbojfbbg_1K_AO.jpg": {
        "fileSize": 203808
    },
    "D:/TRASH/tv\\input\\wood_board_wbojfbbg\\Thumbs\\2k\\wbojfbbg_2K_AO.jpg": {
        "fileSize": 817851
    },
    "D:/TRASH/tv\\input\\wood_board_wbojfbbg\\Thumbs\\1k\\wbojfbbg_1K_Displacement.jpg": {
        "fileSize": 127039
    },
    "D:/TRASH/tv\\input\\wood_board_wbojfbbg\\Thumbs\\2k\\wbojfbbg_2K_Displacement.jpg": {
        "fileSize": 465793
    },
    "D:/TRASH/tv\\input\\wood_board_wbojfbbg\\Thumbs\\4k\\wbojfbbg_4K_Albedo.jpg": {
        "fileSize": 8292355
    },
    "D:/TRASH/tv\\input\\wood_board_wbojfbbg\\Thumbs\\1k\\wbojfbbg_1K_Normal.jpg": {
        "fileSize": 367424
    },
    "D:/TRASH/tv\\input\\wood_board_wbojfbbg\\Thumbs\\2k\\wbojfbbg_2K_Normal.jpg": {
        "fileSize": 1522033
    },
    "D:/TRASH/tv\\input\\wood_parquet_ufipfbmew\\previews\\ufipfbmew_Popup_3840_sp.jpg": {
        "fileSize": 251717
    },
    "D:/TRASH/tv\\input\\wood_board_wbojfbbg\\Thumbs\\4k\\wbojfbbg_4K_AO.jpg": {
        "fileSize": 2961034
    },
    "D:/TRASH/tv\\input\\wood_board_wbojfbbg\\Thumbs\\1k\\wbojfbbg_1K_Roughness.jpg": {
        "fileSize": 269994
    },
    "D:/TRASH/tv\\input\\wood_board_wbojfbbg\\Thumbs\\2k\\wbojfbbg_2K_Roughness.jpg": {
        "fileSize": 1076024
    },
    "D:/TRASH/tv\\input\\wood_board_wbojfbbg\\Thumbs\\4k\\wbojfbbg_4K_Displacement.jpg": {
        "fileSize": 1659016
    },
    "D:/TRASH/tv\\input\\wood_board_wbojfbbg\\Thumbs\\4k\\wbojfbbg_4K_Normal.jpg": {
        "fileSize": 5097035
    },
    "D:/TRASH/tv\\input\\wood_board_wbojfbbg\\Thumbs\\4k\\wbojfbbg_4K_Roughness.jpg": {
        "fileSize": 3902320
    },
    "D:/TRASH/tv\\input\\wood_parquet_ufipfbmew\\Thumbs\\1k\\ufipfbmew_1K_Albedo.jpg": {
        "fileSize": 1229148
    },
    "D:/TRASH/tv\\input\\wood_parquet_ufipfbmew\\Thumbs\\1k\\ufipfbmew_1K_AO.jpg": {
        "fileSize": 91591
    },
    "D:/TRASH/tv\\input\\wood_parquet_ufipfbmew\\Thumbs\\1k\\ufipfbmew_1K_Displacement.jpg": {
        "fileSize": 176741
    },
    "D:/TRASH/tv\\input\\wood_parquet_ufipfbmew\\Thumbs\\1k\\ufipfbmew_1K_Normal.jpg": {
        "fileSize": 756559
    },
    "D:/TRASH/tv\\input\\wood_parquet_ufipfbmew\\Thumbs\\1k\\ufipfbmew_1K_Roughness.jpg": {
        "fileSize": 818450
    },
    "D:/TRASH/tv\\input\\wood_parquet_ufipfbmew\\Thumbs\\2k\\ufipfbmew_2K_Albedo.jpg": {
        "fileSize": 4852472
    },
    "D:/TRASH/tv\\input\\wood_parquet_ufipfbmew\\Thumbs\\2k\\ufipfbmew_2K_AO.jpg": {
        "fileSize": 408782
    },
    "D:/TRASH/tv\\input\\wood_parquet_ufipfbmew\\Thumbs\\2k\\ufipfbmew_2K_Displacement.jpg": {
        "fileSize": 684684
    },
    "D:/TRASH/tv\\input\\wood_parquet_ufipfbmew\\Thumbs\\2k\\ufipfbmew_2K_Normal.jpg": {
        "fileSize": 3681523
    },
    "D:/TRASH/tv\\input\\wood_parquet_ufipfbmew\\Thumbs\\2k\\ufipfbmew_2K_Roughness.jpg": {
        "fileSize": 3253592
    },
    "D:/TRASH/tv\\input\\wood_parquet_ufipfbmew\\Thumbs\\4k\\ufipfbmew_4K_Albedo.jpg": {
        "fileSize": 17420003
    },
    "D:/TRASH/tv\\input\\wood_parquet_ufipfbmew\\Thumbs\\4k\\ufipfbmew_4K_AO.jpg": {
        "fileSize": 1787819
    },
    "D:/TRASH/tv\\input\\wood_plank_viriagk\\previews\\viriagk_Popup_3840_sp.jpg": {
        "fileSize": 226987
    },
    "D:/TRASH/tv\\input\\wood_parquet_ufipfbmew\\Thumbs\\4k\\ufipfbmew_4K_Displacement.jpg": {
        "fileSize": 2700423
    },
    "D:/TRASH/tv\\input\\wood_parquet_ufipfbmew\\Thumbs\\4k\\ufipfbmew_4K_Normal.jpg": {
        "fileSize": 15698684
    },
    "D:/TRASH/tv\\input\\wood_plank_viriagk\\Thumbs\\1k\\viriagk_1K_Albedo.jpg": {
        "fileSize": 639548
    },
    "D:/TRASH/tv\\input\\wood_plank_viriagk\\Thumbs\\2k\\viriagk_2K_Albedo.jpg": {
        "fileSize": 2380746
    },
    "D:/TRASH/tv\\input\\wood_parquet_ufipfbmew\\Thumbs\\4k\\ufipfbmew_4K_Roughness.jpg": {
        "fileSize": 12208854
    },
    "D:/TRASH/tv\\input\\wood_plank_viriagk\\Thumbs\\4k\\viriagk_4K_Albedo.jpg": {
        "fileSize": 8415218
    },
    "D:/TRASH/tv\\input\\wood_plank_wcvieg3n\\previews\\wcvieg3n_Popup_3840_sp.jpg": {
        "fileSize": 317069
    },
    "D:/TRASH/tv\\input\\wood_plank_viriagk\\Thumbs\\2k\\viriagk_2K_AO.jpg": {
        "fileSize": 172069
    },
    "D:/TRASH/tv\\input\\wood_plank_viriagk\\Thumbs\\1k\\viriagk_1K_AO.jpg": {
        "fileSize": 51743
    },
    "D:/TRASH/tv\\input\\wood_plank_viriagk\\Thumbs\\4k\\viriagk_4K_AO.jpg": {
        "fileSize": 591352
    },
    "D:/TRASH/tv\\input\\wood_plank_wcvieg3n\\Thumbs\\1k\\wcvieg3n_1K_Albedo.jpg": {
        "fileSize": 1073720
    },
    "D:/TRASH/tv\\input\\wood_plank_wcvieg3n\\Thumbs\\2k\\wcvieg3n_2K_Albedo.jpg": {
        "fileSize": 4377633
    },
    "D:/TRASH/tv\\input\\wood_plank_wcvieg3n\\Thumbs\\4k\\wcvieg3n_4K_Albedo.jpg": {
        "fileSize": 16673746
    },
    "D:/TRASH/tv\\input\\wood_plank_viriagk\\Thumbs\\1k\\viriagk_1K_Displacement.jpg": {
        "fileSize": 126749
    },
    "D:/TRASH/tv\\input\\wood_plank_viriagk\\Thumbs\\2k\\viriagk_2K_Displacement.jpg": {
        "fileSize": 552218
    },
    "D:/TRASH/tv\\input\\wood_veneer_vdcjfiw\\previews\\vdcjfiw_Popup_3840_sp.jpg": {
        "fileSize": 188242
    },
    "D:/TRASH/tv\\input\\wood_plank_wcvieg3n\\Thumbs\\1k\\wcvieg3n_1K_AO.jpg": {
        "fileSize": 563664
    },
    "D:/TRASH/tv\\input\\wood_plank_wcvieg3n\\Thumbs\\2k\\wcvieg3n_2K_AO.jpg": {
        "fileSize": 2161312
    },
    "D:/TRASH/tv\\input\\wood_plank_viriagk\\Thumbs\\4k\\viriagk_4K_Displacement.jpg": {
        "fileSize": 2437262
    },
    "D:/TRASH/tv\\input\\wood_plank_wcvieg3n\\Thumbs\\4k\\wcvieg3n_4K_AO.jpg": {
        "fileSize": 8142643
    },
    "D:/TRASH/tv\\input\\wood_plank_viriagk\\Thumbs\\2k\\viriagk_2K_Normal.jpg": {
        "fileSize": 1580847
    },
    "D:/TRASH/tv\\input\\wood_plank_viriagk\\Thumbs\\1k\\viriagk_1K_Normal.jpg": {
        "fileSize": 487806
    },
    "D:/TRASH/tv\\input\\wood_plank_wcvieg3n\\Thumbs\\1k\\wcvieg3n_1K_Displacement.jpg": {
        "fileSize": 143482
    },
    "D:/TRASH/tv\\input\\wood_plank_wcvieg3n\\Thumbs\\2k\\wcvieg3n_2K_Displacement.jpg": {
        "fileSize": 547492
    },
    "D:/TRASH/tv\\input\\wood_plank_viriagk\\Thumbs\\4k\\viriagk_4K_Normal.jpg": {
        "fileSize": 4959069
    },
    "D:/TRASH/tv\\input\\wood_plank_wcvieg3n\\Thumbs\\4k\\wcvieg3n_4K_Displacement.jpg": {
        "fileSize": 2296592
    },
    "D:/TRASH/tv\\input\\wood_plank_viriagk\\Thumbs\\2k\\viriagk_2K_Roughness.jpg": {
        "fileSize": 757013
    },
    "D:/TRASH/tv\\input\\wood_plank_viriagk\\Thumbs\\1k\\viriagk_1K_Roughness.jpg": {
        "fileSize": 198162
    },
    "D:/TRASH/tv\\input\\wood_plank_wcvieg3n\\Thumbs\\2k\\wcvieg3n_2K_Normal.jpg": {
        "fileSize": 4592870
    },
    "D:/TRASH/tv\\input\\wood_plank_wcvieg3n\\Thumbs\\1k\\wcvieg3n_1K_Normal.jpg": {
        "fileSize": 978538
    },
    "D:/TRASH/tv\\input\\wood_plank_viriagk\\Thumbs\\4k\\viriagk_4K_Roughness.jpg": {
        "fileSize": 2827329
    },
    "D:/TRASH/tv\\input\\wood_plank_wcvieg3n\\Thumbs\\4k\\wcvieg3n_4K_Normal.jpg": {
        "fileSize": 20392273
    },
    "D:/TRASH/tv\\input\\wood_plank_wcvieg3n\\Thumbs\\2k\\wcvieg3n_2K_Roughness.jpg": {
        "fileSize": 3264225
    },
    "D:/TRASH/tv\\input\\wood_plank_wcvieg3n\\Thumbs\\1k\\wcvieg3n_1K_Roughness.jpg": {
        "fileSize": 808480
    },
    "D:/TRASH/tv\\input\\wood_veneer_vdcjfiw\\Thumbs\\1k\\vdcjfiw_1K_Albedo.jpg": {
        "fileSize": 348961
    },
    "D:/TRASH/tv\\input\\wood_veneer_vdcjfiw\\Thumbs\\2k\\vdcjfiw_2K_Albedo.jpg": {
        "fileSize": 1417604
    },
    "D:/TRASH/tv\\input\\wood_plank_wcvieg3n\\Thumbs\\4k\\wcvieg3n_4K_Roughness.jpg": {
        "fileSize": 12993996
    },
    "D:/TRASH/tv\\input\\wood_veneer_vdcjfiw\\Thumbs\\1k\\vdcjfiw_1K_AO.jpg": {
        "fileSize": 193836
    },
    "D:/TRASH/tv\\input\\wood_veneer_vdcjfiw\\Thumbs\\2k\\vdcjfiw_2K_AO.jpg": {
        "fileSize": 842471
    },
    "D:/TRASH/tv\\input\\wood_veneer_vdcjfiw\\Thumbs\\4k\\vdcjfiw_4K_Albedo.jpg": {
        "fileSize": 5581260
    },
    "D:/TRASH/tv\\input\\wood_veneer_vdcjfiw\\Thumbs\\1k\\vdcjfiw_1K_Displacement.jpg": {
        "fileSize": 104344
    },
    "D:/TRASH/tv\\input\\wood_veneer_vdcjfiw\\Thumbs\\2k\\vdcjfiw_2K_Displacement.jpg": {
        "fileSize": 402774
    },
    "D:/TRASH/tv\\input\\wood_veneer_vdcjfiw\\Thumbs\\1k\\vdcjfiw_1K_Normal.jpg": {
        "fileSize": 375763
    },
    "D:/TRASH/tv\\input\\wood_veneer_vdcjfiw\\Thumbs\\4k\\vdcjfiw_4K_AO.jpg": {
        "fileSize": 3527160
    },
    "D:/TRASH/tv\\input\\wood_veneer_vdcjfiw\\Thumbs\\2k\\vdcjfiw_2K_Normal.jpg": {
        "fileSize": 1917176
    },
    "D:/TRASH/tv\\input\\wood_veneer_vdcjfiw\\Thumbs\\1k\\vdcjfiw_1K_Roughness.jpg": {
        "fileSize": 154475
    },
    "D:/TRASH/tv\\input\\wood_veneer_vdcjfiw\\Thumbs\\4k\\vdcjfiw_4K_Displacement.jpg": {
        "fileSize": 1542438
    },
    "D:/TRASH/tv\\input\\wood_veneer_vdcjfiw\\Thumbs\\2k\\vdcjfiw_2K_Roughness.jpg": {
        "fileSize": 653531
    },
    "D:/TRASH/tv\\input\\wood_veneer_vdcjfiw\\Thumbs\\4k\\vdcjfiw_4K_Normal.jpg": {
        "fileSize": 8267925
    },
    "D:/TRASH/tv\\input\\wood_veneer_vdcjfiw\\Thumbs\\4k\\vdcjfiw_4K_Roughness.jpg": {
        "fileSize": 2809491
    }
}